geometrica/__init__.py
geometrica/transform.py
geometrica/trig.py
geometrica-0.2.0.dist-info/DESCRIPTION.rst
geometrica-0.2.0.dist-info/METADATA
geometrica-0.2.0.dist-info/RECORD
geometrica-0.2.0.dist-info/WHEEL
geometrica-0.2.0.dist-info/metadata.json
geometrica-0.2.0.dist-info/top_level.txt
