Metadata-Version: 2.0
Name: geometrica
Version: 0.2.0
Summary: A pure-Python geometry library
Home-page: https://geometrica.samireland.com
Author: Sam Ireland
Author-email: mail@samireland.com
License: MIT
Keywords: geometry trigonometry coordinates shapes
Platform: UNKNOWN
Classifier: Development Status :: 4 - Beta
Classifier: Intended Audience :: Science/Research
Classifier: License :: OSI Approved :: MIT License
Classifier: Topic :: Scientific/Engineering :: Mathematics
Classifier: Programming Language :: Python :: 3
Classifier: Programming Language :: Python :: 3.0
Classifier: Programming Language :: Python :: 3.1
Classifier: Programming Language :: Python :: 3.2
Classifier: Programming Language :: Python :: 3.3
Classifier: Programming Language :: Python :: 3.4
Classifier: Programming Language :: Python :: 3.5
Classifier: Programming Language :: Python :: 3.6
Requires-Dist: matrices
